sysmon/__init__.py
sysmon/__main__.py
sysmon/gather_data.py
sysmon/sysmon.py
sysmon/sysmonitor.ui
sysmon-1.0.1.dist-info/METADATA
sysmon-1.0.1.dist-info/WHEEL
sysmon-1.0.1.dist-info/entry_points.txt
sysmon-1.0.1.dist-info/top_level.txt
sysmon-1.0.1.dist-info/RECORD
