Metadata-Version: 2.1
Name: sysmon
Version: 1.0.1
Summary: System Monitor for Linux
Home-page: https://github.com/MatthiasSchinzel/sysmon
Author: Matthias Schinzel
Author-email: unused@unused.com
License: UNKNOWN
Platform: UNKNOWN
Classifier: Programming Language :: Python :: 3
Classifier: License :: OSI Approved :: GNU General Public License v3 (GPLv3)
Classifier: Operating System :: POSIX :: Linux
Requires-Python: >=3.6
Requires-Dist: pyqtgraph
Requires-Dist: pyqt5 (>=5)
Requires-Dist: numpy (>=1)
